lansonai/__init__.py
lansonai/vadtools/__init__.py
lansonai/vadtools/api.py
lansonai/vadtools/config/settings.py
lansonai/vadtools/core/audio_processor.py
lansonai/vadtools/core/utils.py
lansonai/vadtools/core/vad_detector.py
lansonai_vadtools-0.2.0.dist-info/METADATA
lansonai_vadtools-0.2.0.dist-info/WHEEL
lansonai_vadtools-0.2.0.dist-info/RECORD
