Metadata-Version: 2.4
Name: lansonai-vadtools
Version: 0.2.0
Summary: Voice Activity Detection (VAD) package for audio/video processing
Project-URL: Homepage, https://github.com/lansonai/vadtools
Project-URL: Documentation, https://github.com/lansonai/vadtools
Project-URL: Repository, https://github.com/lansonai/vadtools
Author-email: LansonAI <info@lansonai.com>
License: MIT
Keywords: audio,speech,vad,video,voice-activity-detection
Classifier: Development Status :: 4 - Beta
Classifier: Intended Audience :: Developers
Classifier: License :: OSI Approved :: MIT License
Classifier: Programming Language :: Python :: 3
Classifier: Programming Language :: Python :: 3.12
Classifier: Topic :: Multimedia :: Sound/Audio :: Analysis
Requires-Python: >=3.12
Requires-Dist: librosa>=0.10.0
Requires-Dist: numpy>=1.24.0
Requires-Dist: soundfile>=0.12.0
Requires-Dist: torch>=2.0.0
Requires-Dist: torchaudio>=2.0.0
Provides-Extra: dev
Requires-Dist: aiofiles; extra == 'dev'
Requires-Dist: fastapi==0.116.1; extra == 'dev'
Requires-Dist: psycopg2-binary==2.9.9; extra == 'dev'
Requires-Dist: pydantic==2.11.7; extra == 'dev'
Requires-Dist: python-multipart==0.0.20; extra == 'dev'
Requires-Dist: uvicorn==0.35.0; extra == 'dev'
Provides-Extra: test
Requires-Dist: pytest-cov>=4.0.0; extra == 'test'
Requires-Dist: pytest>=7.0.0; extra == 'test'
